hilcat/__init__.py
hilcat/_dist_ver.py
hilcat/core.py
hilcat/version.py
hilcat/db/__init__.py
hilcat/db/es.py
hilcat/db/mysql.py
hilcat/db/postgresql.py
hilcat/db/redis.py
hilcat/db/sqlite.py
hilcat/db/relational/__init__.py
hilcat/db/relational/adapter.py
hilcat/db/relational/cache.py
hilcat/db/relational/config.py
hilcat/db/relational/decoder.py
hilcat/db/relational/encoder.py
hilcat/db/relational/sql.py
hilcat/third/__init__.py
hilcat/third/sqlitedict.py
hilcat-1.3.2.dist-info/METADATA
hilcat-1.3.2.dist-info/WHEEL
hilcat-1.3.2.dist-info/top_level.txt
hilcat-1.3.2.dist-info/RECORD
