Metadata-Version: 2.4
Name: hilcat
Version: 1.3.2
Summary: High Level Cache Tool.
Author-email: darkpeath <darkpeath@gmail.com>
Project-URL: Homepage, https://github.com/darkpeath/hilcat
